pykemon_battle/__init__.py
pykemon_battle/battle.py
pykemon_battle/move.py
pykemon_battle/pokemon.py
pykemon_battle/utils/__init__.py
pykemon_battle/utils/battle_dynamics.py
pykemon_battle/utils/constants.py
pykemon_battle/utils/terminal_background.py
pykemon_battle/utils/text_display.py
pykemon_battle/utils/utilities.py
pykemon_battle-0.0.3.dist-info/LICENSE
pykemon_battle-0.0.3.dist-info/WHEEL
pykemon_battle-0.0.3.dist-info/METADATA
pykemon_battle-0.0.3.dist-info/RECORD
